mergram/__init__.py
mergram/flowchart.py
mergram-0.3.0.dist-info/licenses/LICENSE
mergram-0.3.0.dist-info/METADATA
mergram-0.3.0.dist-info/WHEEL
mergram-0.3.0.dist-info/top_level.txt
mergram-0.3.0.dist-info/RECORD
