Metadata-Version: 2.4
Name: mergram
Version: 0.3.0
Summary: Programmatically construct Mermaid diagrams and charts in Python
Author-email: "Blake A. Wilson" <blakeaw1102@gmail.com>
License: MIT
Project-URL: Repository, https://github.com/blakeaw/mergram
Project-URL: Issues, https://github.com/blakeaw/mergram/issues
Project-URL: Changelog, https://github.com/blakeaw/mergram/blob/main/CHANGELOG.md
Classifier: Programming Language :: Python :: 3
Classifier: License :: OSI Approved :: MIT License
Classifier: Operating System :: OS Independent
Requires-Python: >=3.8
License-File: LICENSE
Provides-Extra: networkx
Requires-Dist: networkx; extra == "networkx"
Dynamic: license-file
